{"imagePath":"texture.png","SubTexture":[{"width":58,"y":231,"height":92,"name":"M_animation/Basic/Ear/L_hand_up3","x":721},{"y":604,"frameX":-1,"frameHeight":84,"frameY":-3,"width":104,"frameWidth":112,"height":79,"name":"M_animation/Basic/Mouth/Smile_L_hand2","x":930},{"y":341,"frameX":0,"frameHeight":63,"frameY":-1,"width":60,"frameWidth":62,"height":62,"name":"M_animation/Basic/Error/L_hand_fist","x":1018},{"width":46,"y":132,"height":59,"name":"body part/L_hand","x":1083},{"width":59,"y":145,"height":92,"name":"M_animation/Basic/Eye/L_hand_up2","x":1022},{"width":91,"y":242,"height":70,"name":"M_animation/Basic/Eye/L_hand_up3","x":876},{"width":64,"y":239,"height":55,"name":"M_animation/Basic/Ear/L_hand_up1","x":1034},{"y":1,"frameX":0,"frameHeight":52,"frameY":0,"width":115,"frameWidth":115,"height":51,"name":"M_animation/Basic/Eye/L_hand_up4","x":899},{"width":63,"y":242,"height":97,"name":"M_animation/Basic/Ear/L_hand_up2","x":969},{"y":1,"frameX":-1,"frameHeight":65,"frameY":0,"width":79,"frameWidth":80,"height":65,"name":"M_animation/Basic/Mouth/Smile_L_hand1","x":1066},{"y":928,"frameX":0,"frameHeight":78,"frameY":-1,"width":83,"frameWidth":83,"height":77,"name":"M_animation/Basic/Eye/L_lower_arm_up2","x":530},{"y":341,"frameX":-1,"frameHeight":109,"frameY":0,"width":47,"frameWidth":48,"height":109,"name":"M_animation/Basic/Ear/L_lower_arm_up1","x":969},{"y":807,"frameX":-1,"frameHeight":143,"frameY":-1,"width":42,"frameWidth":43,"height":142,"name":"body part/L_lower_arm","x":869},{"y":664,"frameX":-1,"frameHeight":178,"frameY":-4,"width":96,"frameWidth":97,"height":174,"name":"body part/L_upper_arm","x":723},{"y":488,"frameX":-1,"frameHeight":174,"frameY":0,"width":96,"frameWidth":97,"height":174,"name":"M_animation/Basic/Ear/L_upper_arm_up1","x":632},{"width":204,"y":729,"height":102,"name":"M_animation/Basic/Ear/L_upper_arm_up2","x":269},{"width":71,"y":68,"height":62,"name":"body part/Neck","x":1066},{"y":520,"frameX":0,"frameHeight":63,"frameY":-1,"width":60,"frameWidth":62,"height":62,"name":"M_animation/Basic/Error/R_hand_fist","x":1009},{"y":807,"frameX":-1,"frameHeight":59,"frameY":0,"width":46,"frameWidth":47,"height":59,"name":"body part/R_hand","x":913},{"y":833,"frameX":-1,"frameHeight":93,"frameY":0,"width":204,"frameWidth":205,"height":93,"name":"body part/Pants","x":419},{"y":1,"frameX":0,"frameHeight":143,"frameY":-1,"width":42,"frameWidth":43,"height":142,"name":"body part/R_lower_arm","x":1022},{"y":728,"frameX":-1,"frameHeight":174,"frameY":0,"width":96,"frameWidth":99,"height":174,"name":"body part/R_upper_arm","x":625},{"y":224,"frameX":0,"frameHeight":149,"frameY":-1,"width":212,"frameWidth":212,"height":148,"name":"body part/Waist","x":381},{"y":852,"frameX":-1,"frameHeight":172,"frameY":-1,"width":207,"frameWidth":210,"height":169,"name":"body part/Chest","x":1},{"y":852,"frameX":0,"frameHeight":168,"frameY":-1,"width":207,"frameWidth":208,"height":167,"name":"M_animation/Basic/Ear/Chest_up","x":210},{"width":72,"y":70,"height":105,"name":"head part/R_ear","x":816},{"width":72,"y":468,"height":106,"name":"head part/L_ear","x":935},{"y":374,"frameX":-1,"frameHeight":112,"frameY":0,"width":150,"frameWidth":151,"height":112,"name":"M_animation/Basic/Ear/Red scarf_up","x":518},{"y":607,"frameX":-2,"frameHeight":119,"frameY":0,"width":148,"frameWidth":150,"height":119,"name":"others/Red scarf","x":482},{"y":177,"frameX":-1,"frameHeight":47,"frameY":0,"width":46,"frameWidth":48,"height":47,"name":"others/Badge","x":816},{"y":1,"frameX":0,"frameHeight":384,"frameY":0,"width":378,"frameWidth":378,"height":381,"name":"head part/Head","x":1},{"y":969,"frameX":0,"frameHeight":49,"frameY":-2,"width":100,"frameWidth":100,"height":47,"name":"M_animation/Basic/Ear/Mouth2","x":760},{"width":82,"y":314,"height":37,"name":"head part/Mouth","x":876},{"y":951,"frameX":0,"frameHeight":70,"frameY":0,"width":76,"frameWidth":77,"height":70,"name":"M_animation/Basic/Ear/Mouth3","x":869},{"y":177,"frameX":0,"frameHeight":64,"frameY":-1,"width":112,"frameWidth":112,"height":63,"name":"M_animation/Basic/Mouth/Smile_mouth1","x":876},{"width":152,"y":741,"height":64,"name":"M_animation/Basic/Mouth/Smile_mouth2","x":821},{"y":664,"frameX":0,"frameHeight":56,"frameY":-1,"width":86,"frameWidth":86,"height":54,"name":"M_animation/Basic/Nose/Sniff_mouth1","x":632},{"y":616,"frameX":0,"frameHeight":38,"frameY":0,"width":86,"frameWidth":86,"height":35,"name":"M_animation/Basic/Nose/Sniff_mouth2","x":730},{"width":133,"y":904,"height":104,"name":"M_animation/Basic/Nose/Sniff_L_eye2","x":625},{"width":107,"y":487,"height":127,"name":"head part/L_eye","x":730},{"y":840,"frameX":-1,"frameHeight":127,"frameY":0,"width":107,"frameWidth":108,"height":127,"name":"M_animation/Basic/Eye/L_eye_no_eyeball","x":760},{"y":616,"frameX":-3,"frameHeight":124,"frameY":0,"width":107,"frameWidth":112,"height":123,"name":"小M动画/眨眼-眼部替换动画/L_eye_close","x":821},{"y":107,"frameX":-1,"frameHeight":111,"frameY":0,"width":86,"frameWidth":87,"height":111,"name":"M_animation/Basic/Mouth/Smile_L_eye1","x":630},{"y":355,"frameX":0,"frameHeight":129,"frameY":-2,"width":89,"frameWidth":89,"height":127,"name":"M_animation/Basic/Mouth/Smile_L_eye2","x":781},{"y":729,"frameX":0,"frameHeight":91,"frameY":-4,"width":146,"frameWidth":147,"height":86,"name":"M_animation/Basic/Nose/Sniff_L_eye1","x":475},{"y":173,"frameX":-2,"frameHeight":38,"frameY":0,"width":17,"frameWidth":20,"height":36,"name":"M_animation/Basic/Nose/Sniff_snot5","x":990},{"y":70,"frameX":-1,"frameHeight":36,"frameY":-4,"width":16,"frameWidth":18,"height":31,"name":"M_animation/Basic/Nose/Sniff_snot3","x":776},{"width":16,"y":211,"height":21,"name":"M_animation/Basic/Nose/Sniff_snot1","x":990},{"y":70,"frameX":-1,"frameHeight":33,"frameY":0,"width":16,"frameWidth":17,"height":32,"name":"M_animation/Basic/Nose/Sniff_snot4","x":758},{"y":70,"frameX":-1,"frameHeight":29,"frameY":0,"width":16,"frameWidth":17,"height":28,"name":"M_animation/Basic/Nose/Sniff_snot2","x":794},{"y":355,"frameX":0,"frameHeight":113,"frameY":0,"width":95,"frameWidth":95,"height":111,"name":"M_animation/Basic/Nose/Sniff_nose2","x":872},{"y":384,"frameX":0,"frameHeight":232,"frameY":0,"width":266,"frameWidth":267,"height":232,"name":"M_animation/Basic/Error/L_expression_1","x":1},{"y":70,"frameX":0,"frameHeight":102,"frameY":-1,"width":64,"frameWidth":65,"height":101,"name":"M_animation/Basic/Nose/Sniff_nose3","x":956},{"y":1,"frameX":0,"frameHeight":223,"frameY":-2,"width":247,"frameWidth":249,"height":221,"name":"M_animation/Basic/Error/L_expression_2","x":381},{"y":70,"frameX":-1,"frameHeight":101,"frameY":0,"width":64,"frameWidth":66,"height":101,"name":"head part/Nose","x":890},{"width":266,"y":618,"height":232,"name":"M_animation/Basic/Error/R_expression_1","x":1},{"y":384,"frameX":-1,"frameHeight":221,"frameY":0,"width":247,"frameWidth":248,"height":221,"name":"M_animation/Basic/Error/R_expression_2","x":269},{"y":352,"frameX":0,"frameHeight":134,"frameY":0,"width":109,"frameWidth":109,"height":133,"name":"M_animation/Basic/Nose/Sniff_nose1","x":670},{"y":840,"frameX":0,"frameHeight":53,"frameY":0,"width":35,"frameWidth":36,"height":52,"name":"others/Armband","x":723},{"y":1,"frameX":0,"frameHeight":72,"frameY":-5,"width":139,"frameWidth":140,"height":67,"name":"M_animation/Basic/Nose/Sniff_R_eye1","x":758},{"y":1,"frameX":-1,"frameHeight":104,"frameY":0,"width":126,"frameWidth":127,"height":104,"name":"M_animation/Basic/Nose/Sniff_R_eye2","x":630},{"y":107,"frameX":0,"frameHeight":122,"frameY":0,"width":93,"frameWidth":97,"height":122,"name":"head part/R_eye","x":721},{"y":231,"frameX":0,"frameHeight":122,"frameY":0,"width":93,"frameWidth":95,"height":122,"name":"M_animation/Basic/Eye/R_eye_no_eyeball","x":781},{"y":484,"frameX":0,"frameHeight":118,"frameY":0,"width":94,"frameWidth":95,"height":118,"name":"小M动画/眨眼-眼部替换动画/R_eye_close","x":839},{"y":452,"frameX":-2,"frameHeight":67,"frameY":0,"width":65,"frameWidth":69,"height":66,"name":"others/Shit","x":1009},{"y":685,"frameX":-1,"frameHeight":53,"frameY":-3,"width":63,"frameWidth":64,"height":49,"name":"M_animation/Basic/Error/Tear","x":930},{"y":224,"frameX":-18,"frameHeight":146,"frameY":-11,"width":124,"frameWidth":163,"height":126,"name":"M_animation/Basic/Mouth/Smile_L_facered","x":595},{"y":488,"frameX":-6,"frameHeight":102,"frameY":0,"width":109,"frameWidth":122,"height":102,"name":"M_animation/Basic/Mouth/Peach_pink","x":518},{"y":928,"frameX":-2,"frameHeight":92,"frameY":0,"width":109,"frameWidth":114,"height":92,"name":"M_animation/Basic/Mouth/Peach_white","x":419},{"y":452,"frameX":-2,"frameHeight":19,"frameY":-3,"width":14,"frameWidth":19,"height":12,"name":"M_animation/Basic/Eye/R_eyeball","x":969},{"width":211,"y":607,"height":120,"name":"M_animation/Basic/Eye/Xinjiangcap","x":269}],"name":"skeleton"}